[
  {
    "id": 1,
    "question": "भारत में संसाधनों के संरक्षण के कौन-कौन से तरीके अपनाए गए हैं? / What are the methods adopted for resource conservation in India?",
    "options": {
      "A": "संसाधनों का पुनः उपयोग / Reuse of resources",
      "B": "कृषि में रासायनिक उर्वरकों का अत्यधिक उपयोग / Excessive use of chemical fertilizers",
      "C": "अपशिष्ट पदार्थों का पुनर्चक्रण / Recycling of waste materials",
      "D": "वनों की अंधाधुंध कटाई / Indiscriminate deforestation"
    },
    "answer": ["A", "C"]
  },
  {
    "id": 2,
    "question": "भारत की किस भौगोलिक विशेषता के कारण मानसून की दिशा बदलती है? / Which geographical feature in India alters the direction of monsoon?",
    "options": {
      "A": "थार मरुस्थल / Thar Desert",
      "B": "पश्चिमी घाट / Western Ghats",
      "C": "हिमालय पर्वत / Himalayan Mountains",
      "D": "सुंदरबन डेल्टा / Sunderban Delta"
    },
    "answer": ["A", "C"]
  },
  {
    "id": 3,
    "question": "कौन-कौन सी नदियाँ पेरिनियल (बारहमासी) हैं? / Which rivers are perennial in India?",
    "options": {
      "A": "गंगा / Ganga",
      "B": "गोदावरी / Godavari",
      "C": "ब्रह्मपुत्र / Brahmaputra",
      "D": "कावेरी / Kaveri"
    },
    "answer": ["A", "C"]
  },
  {
    "id": 4,
    "question": "भारत में भू-स्खलन के मुख्य कारण कौन से हैं? / What are the major causes of landslides in India?",
    "options": {
      "A": "वनों की कटाई / Deforestation",
      "B": "अत्यधिक वर्षा / Heavy rainfall",
      "C": "पवन अपरदन / Wind erosion",
      "D": "भूकंप / Earthquake"
    },
    "answer": ["A", "B", "D"]
  },
  {
    "id": 5,
    "question": "खारे जल की झीलों में कौन-कौन सी झीलें आती हैं? / Which of the following are saline water lakes?",
    "options": {
      "A": "चिल्का / Chilika",
      "B": "सांभर / Sambhar",
      "C": "वुलर / Wular",
      "D": "पुलिकट / Pulicat"
    },
    "answer": ["A", "B", "D"]
  },
  {
    "id": 6,
    "question": "कौन-से राज्य मुख्यतः ब्लैक सॉइल रीजन में आते हैं? / Which states lie primarily in black soil region?",
    "options": {
      "A": "मध्य प्रदेश / Madhya Pradesh",
      "B": "महाराष्ट्र / Maharashtra",
      "C": "पश्चिम बंगाल / West Bengal",
      "D": "गुजरात / Gujarat"
    },
    "answer": ["A", "B", "D"]
  },
  {
    "id": 7,
    "question": "किस कृषि पद्धति को 'विनाशकारी कृषि' कहा जाता है? / Which agricultural practice is called 'destructive agriculture'?",
    "options": {
      "A": "झूम खेती / Shifting cultivation",
      "B": "कृषि वानिकी / Agroforestry",
      "C": "व्यापक सिंचाई आधारित कृषि / Extensive irrigation farming",
      "D": "एकल फसल कृषि / Monoculture"
    },
    "answer": ["A", "D"]
  },
  {
    "id": 8,
    "question": "भारत में कौन-कौन सी ऊर्जा स्रोत अक्षय हैं? / Which of the following energy sources are renewable?",
    "options": {
      "A": "सौर ऊर्जा / Solar energy",
      "B": "पेट्रोलियम / Petroleum",
      "C": "जल ऊर्जा / Hydropower",
      "D": "कोयला / Coal"
    },
    "answer": ["A", "C"]
  },
  {
    "id": 9,
    "question": "भारत में मिट्टी अपरदन को कैसे रोका जा सकता है? / How can soil erosion be prevented in India?",
    "options": {
      "A": "वृक्षारोपण / Afforestation",
      "B": "झूम खेती / Shifting cultivation",
      "C": "कंटूर खेती / Contour ploughing",
      "D": "ओवरग्रेजिंग / Overgrazing"
    },
    "answer": ["A", "C"]
  },
  {
    "id": 10,
    "question": "मानव निर्मित संसाधनों में क्या-क्या आता है? / Which of the following are man-made resources?",
    "options": {
      "A": "बिजली / Electricity",
      "B": "बंदरगाह / Ports",
      "C": "पेट्रोल / Petroleum",
      "D": "सड़कें / Roads"
    },
    "answer": ["A", "B", "D"]
  },
  {
    "id": 11,
    "question": "भारत के किस भाग में वर्षा की मात्रा सबसे कम होती है? / Which region receives the least rainfall in India?",
    "options": {
      "A": "लेह / Leh",
      "B": "जैसलमेर / Jaisalmer",
      "C": "मुंबई / Mumbai",
      "D": "कोहिमा / Kohima"
    },
    "answer": ["A", "B"]
  },
  {
    "id": 12,
    "question": "मानव विकास सूचकांक (HDI) किन आधारों पर होता है? / HDI is based on which indicators?",
    "options": {
      "A": "प्रति व्यक्ति आय / Per capita income",
      "B": "शिक्षा स्तर / Education level",
      "C": "स्वास्थ्य स्तर / Health index",
      "D": "धार्मिक विविधता / Religious diversity"
    },
    "answer": ["A", "B", "C"]
  },
  {
    "id": 13,
    "question": "नदियों द्वारा निर्मित स्थल रूप कौन-कौन से हैं? / Which landforms are formed by rivers?",
    "options": {
      "A": "डेल्टा / Delta",
      "B": "प्लाया / Playa",
      "C": "कटाव घाटियाँ / Gorges",
      "D": "जलोढ़ मैदान / Alluvial plains"
    },
    "answer": ["A", "C", "D"]
  },
  {
    "id": 14,
    "question": "भारत के किन क्षेत्रों में शुष्क जलवायु पाई जाती है? / In which regions is arid climate found in India?",
    "options": {
      "A": "राजस्थान / Rajasthan",
      "B": "कच्छ का रन / Rann of Kutch",
      "C": "तमिलनाडु / Tamil Nadu",
      "D": "मेघालय / Meghalaya"
    },
    "answer": ["A", "B"]
  },
  {
    "id": 15,
    "question": "खनिज संसाधनों की विशेषताएँ क्या हैं? / What are the characteristics of mineral resources?",
    "options": {
      "A": "अक्षय हैं / Renewable",
      "B": "सीमित मात्रा में हैं / Finite in quantity",
      "C": "लंबे समय में बनते हैं / Formed over long geological periods",
      "D": "मानव द्वारा निर्मित हैं / Man-made"
    },
    "answer": ["B", "C"]
  },
  {
    "id": 16,
    "question": "जलवायु पर किस-किस कारक का प्रभाव होता है? / Which factors affect climate?",
    "options": {
      "A": "ऊँचाई / Altitude",
      "B": "समुद्र से दूरी / Distance from sea",
      "C": "वनस्पति / Vegetation",
      "D": "धार्मिक आस्था / Religious beliefs"
    },
    "answer": ["A", "B", "C"]
  },
  {
    "id": 17,
    "question": "किस फसल को 'खरीफ फसल' कहा जाता है? / Which are considered Kharif crops?",
    "options": {
      "A": "धान / Rice",
      "B": "गेहूँ / Wheat",
      "C": "मक्का / Maize",
      "D": "बाजरा / Bajra"
    },
    "answer": ["A", "C", "D"]
  },
  {
    "id": 18,
    "question": "जलवायु परिवर्तन के क्या-क्या प्रभाव हो सकते हैं? / What are the impacts of climate change?",
    "options": {
      "A": "समुद्र स्तर में वृद्धि / Rise in sea level",
      "B": "फसल उत्पादन में गिरावट / Decline in crop yield",
      "C": "सर्दियों की अवधि बढ़ना / Longer winters",
      "D": "ग्लेशियरों का पिघलना / Melting of glaciers"
    },
    "answer": ["A", "B", "D"]
  },
  {
    "id": 19,
    "question": "भारत के किस क्षेत्र में जलोढ़ मिट्टी पाई जाती है? / Where is alluvial soil found in India?",
    "options": {
      "A": "गंगा का मैदान / Gangetic plains",
      "B": "थार मरुस्थल / Thar desert",
      "C": "ब्रह्मपुत्र घाटी / Brahmaputra valley",
      "D": "दक्षिण पठार / Deccan plateau"
    },
    "answer": ["A", "C"]
  },
  {
    "id": 20,
    "question": "भारत में जनसंख्या घनत्व अधिक क्यों है? / Why is population density high in India?",
    "options": {
      "A": "कृषि प्रधान अर्थव्यवस्था / Agriculture-based economy",
      "B": "सुलभ जलवायु / Favorable climate",
      "C": "प्राकृतिक आपदाओं की कमी / Lack of natural disasters",
      "D": "उपजाऊ मिट्टी / Fertile soil"
    },
    "answer": ["A", "B", "D"]
  }
]
